plico_interferometer_server/__init__.py
plico_interferometer_server/__version__.py
plico_interferometer_server/calib/__init__.py
plico_interferometer_server/conf/plico_interferometer_server.conf
plico_interferometer_server/controller/__init__.py
plico_interferometer_server/controller/controller.py
plico_interferometer_server/controller/plico_interferometer_run_controller.py
plico_interferometer_server/controller/runner.py
plico_interferometer_server/devices/WCF_interface_for_4SightFocus.py
plico_interferometer_server/devices/__init__.py
plico_interferometer_server/devices/abstract_interferometer.py
plico_interferometer_server/devices/phase_cam_4020.py
plico_interferometer_server/devices/phase_cam_4030.py
plico_interferometer_server/devices/simulated_interferometer.py
plico_interferometer_server/devices/wyko4100.py
plico_interferometer_server/i4sight2/Commons.py
plico_interferometer_server/i4sight2/Controller.py
plico_interferometer_server/i4sight2/Server.py
plico_interferometer_server/i4sight2/__init__.py
plico_interferometer_server/process_monitor/__init__.py
plico_interferometer_server/process_monitor/plico_interferometer_run_process_monitor.py
plico_interferometer_server/process_monitor/runner.py
plico_interferometer_server/scripts/__init__.py
plico_interferometer_server/scripts/controller_1.py
plico_interferometer_server/scripts/controller_2.py
plico_interferometer_server/scripts/kill_processes.py
plico_interferometer_server/scripts/process_monitor.py
plico_interferometer_server/scripts/stop.py
plico_interferometer_server/utils/__init__.py
plico_interferometer_server/utils/constants.py
plico_interferometer_server/utils/process_startup_helper.py
plico_interferometer_server/utils/starter_script_creator.py
plico_interferometer_server-0.3.2.dist-info/LICENSE
plico_interferometer_server-0.3.2.dist-info/METADATA
plico_interferometer_server-0.3.2.dist-info/WHEEL
plico_interferometer_server-0.3.2.dist-info/entry_points.txt
plico_interferometer_server-0.3.2.dist-info/top_level.txt
plico_interferometer_server-0.3.2.dist-info/RECORD
